LICENSE
axosyslog_cfg_helper/__init__.py
axosyslog_cfg_helper/axosyslog-cfg-helper.db
axosyslog_cfg_helper/build_db.py
axosyslog_cfg_helper/console.py
axosyslog_cfg_helper/driver_db/__init__.py
axosyslog_cfg_helper/driver_db/block.py
axosyslog_cfg_helper/driver_db/driver.py
axosyslog_cfg_helper/driver_db/driver_db.py
axosyslog_cfg_helper/driver_db/exceptions.py
axosyslog_cfg_helper/driver_db/option.py
axosyslog_cfg_helper/driver_db/utils.py
axosyslog_cfg_helper/generate_diff.py
axosyslog_cfg_helper/globals.py
axosyslog_cfg_helper/module_loader/__init__.py
axosyslog_cfg_helper/module_loader/load_modules.py
axosyslog_cfg_helper/module_loader/parse_sentence.py
axosyslog_cfg_helper-1.19.0.dist-info/METADATA
axosyslog_cfg_helper-1.19.0.dist-info/WHEEL
axosyslog_cfg_helper-1.19.0.dist-info/entry_points.txt
axosyslog_cfg_helper-1.19.0.dist-info/licenses/LICENSE
axosyslog_cfg_helper-1.19.0.dist-info/RECORD
