Metadata-Version: 2.4
Name: axosyslog-cfg-helper
Version: 1.19.0
Summary: Configuration helper for axosyslog.
License: GPL-3.0-only
License-File: LICENSE
Keywords: axosyslog,configuration,cfg
Author: Attila Szakacs
Author-email: szakacs.attila96@gmail.com
Requires-Python: >=3.9,<4.0
Classifier: Environment :: Console
Classifier: License :: OSI Approved :: GNU General Public License v3 (GPLv3)
Classifier: Operating System :: OS Independent
Classifier: Programming Language :: Python :: 3
Classifier: Programming Language :: Python :: 3.9
Classifier: Programming Language :: Python :: 3.10
Classifier: Programming Language :: Python :: 3.11
Classifier: Programming Language :: Python :: 3.12
Classifier: Programming Language :: Python :: 3.13
Classifier: Programming Language :: Python :: 3.14
Classifier: Topic :: System :: Networking
Classifier: Topic :: System :: Systems Administration
Project-URL: Homepage, https://github.com/alltilla/axosyslog-cfg-helper
Project-URL: Repository, https://github.com/alltilla/axosyslog-cfg-helper
